{
  "timestamp": "2025-12-10T17:59:17.633Z",
  "symbols": {
    "QQQ": {
      "price": 623.81,
      "change": null,
      "change_pct": null,
      "volume": 16851331,
      "implied_volatility": 28.97,
      "max_pain": 624
    },
    "SPY": {
      "price": 683.5245,
      "change": null,
      "change_pct": null,
      "volume": 21397267,
      "implied_volatility": 24.24,
      "max_pain": null
    },
    "VIX": {
      "price": 16.99,
      "change": 0.06,
      "change_pct": 0.35,
      "volume": null,
      "implied_volatility": null,
      "day_high": 17.66,
      "day_low": 16.84,
      "year_high": 60.13,
      "year_low": 13.24
    }
  }
}