{
  "timestamp": "2025-12-12T16:26:40.770Z",
  "hours_analyzed": 24,
  "sentiment": {
    "overall": "BULLISH",
    "confidence_pct": 69,
    "sources": {
      "social": {
        "bullish": 71,
        "bearish": 30,
        "neutral": 82,
        "total": 183,
        "pct": 39
      },
      "news": {
        "bullish": 13,
        "bearish": 12,
        "neutral": 8,
        "total": 33,
        "pct": 39
      },
      "video": {
        "bullish": 9,
        "bearish": 1,
        "neutral": 3,
        "total": 13,
        "pct": 69
      },
      "chat": {
        "bullish": 1,
        "bearish": 0,
        "neutral": 3,
        "total": 4,
        "pct": 25
      }
    }
  },
  "analysis": {
    "narrative": "📊 **Consensus:** Mixed sentiment with medium conviction - bullish structural themes clash with near-term technical and execution risks. Professional trader shows bullish positioning but lacks detailed commentary, while retail/analyst sentiment is predominantly bullish (70-90%) against more cautious institutional RSS narrative.\n\n📈 **Themes:** (1) AI infrastructure momentum competing against execution delays and demand questions, (2) Fed monetary policy pivot and liquidity expansion expectations supporting risk assets, (3) Institutional positioning dynamics showing both dark pool accumulation and crowded long exposure creating fragility.\n\n🎯 **Levels:** SPX support at 6843 (10-session pivot), SPY resistance at 690-693-700 (options strikes), support at 688.96 (dark pool level), QQQ resistance at 630-640 (options strikes), support at 605, TSLA critical level at 454.",
    "key_tickers": [
      "SPY",
      "QQQ",
      "SPX",
      "TSLA",
      "BTC"
    ],
    "key_themes": [
      "AI infrastructure execution risk vs structural adoption momentum",
      "Fed liquidity expansion and monetary easing expectations",
      "Institutional positioning crowding and fragility",
      "Technical deterioration signals competing with dark pool accumulation",
      "Consumer discretionary and enterprise software demand weakness"
    ],
    "risk_factors": [
      "SPX break below 6843 triggers cascade to 30-DMA and confirms distribution over consolidation",
      "Oracle AI data center delay signals broader capex execution risk undermining infrastructure thesis",
      "Crowded positioning and bubble valuations create limited pullback tolerance",
      "Earnings misses in enterprise software and consumer discretionary contradicting structural growth narrative",
      "Technical failures at resistance (SPY 690-700, QQQ 640) with volume weakness suggesting institutional distribution"
    ],
    "intraday_bias": "NEUTRAL",
    "intraday_levels": "SPY 688.96 pivot, 690 resistance; SPX 6843 support critical; QQQ 605 support",
    "swing_bias": "BEARISH",
    "swing_levels": "SPY 693-700 resistance cluster, 688.96 breakdown trigger; SPX 6843 key pivot to 30-DMA on break; QQQ 630-640 resistance, 605 support; TSLA 454 must hold",
    "source_alignment": "MIXED"
  },
  "metadata": {
    "model": "AI Model",
    "generation_time_ms": 175207
  },
  "trending": {
    "macro": [
      {
        "ticker": "SPY",
        "mentions": 6,
        "sentiment_score": 0.273,
        "sentiment_label": "Bullish",
        "sentiment_pct": 27,
        "counts": {
          "bullish": 3,
          "bearish": 1,
          "neutral": 2,
          "total": 6
        }
      },
      {
        "ticker": "IWM",
        "mentions": 3,
        "sentiment_score": 0.513,
        "sentiment_label": "Bullish",
        "sentiment_pct": 51,
        "counts": {
          "bullish": 2,
          "bearish": 0,
          "neutral": 1,
          "total": 3
        }
      },
      {
        "ticker": "QQQ",
        "mentions": 3,
        "sentiment_score": -0.25,
        "sentiment_label": "Bearish",
        "sentiment_pct": 25,
        "counts": {
          "bullish": 0,
          "bearish": 1,
          "neutral": 2,
          "total": 3
        }
      },
      {
        "ticker": "GLD",
        "mentions": 2,
        "sentiment_score": 0.035,
        "sentiment_label": "Neutral",
        "sentiment_pct": 4,
        "counts": {
          "bullish": 1,
          "bearish": 1,
          "neutral": 0,
          "total": 2
        }
      },
      {
        "ticker": "SLV",
        "mentions": 2,
        "sentiment_score": 0.035,
        "sentiment_label": "Neutral",
        "sentiment_pct": 4,
        "counts": {
          "bullish": 1,
          "bearish": 1,
          "neutral": 0,
          "total": 2
        }
      }
    ],
    "crypto": [
      {
        "ticker": "BTC",
        "mentions": 4,
        "sentiment_score": -0.108,
        "sentiment_label": "Bearish",
        "sentiment_pct": 11,
        "counts": {
          "bullish": 1,
          "bearish": 2,
          "neutral": 1,
          "total": 4
        }
      },
      {
        "ticker": "MSTR",
        "mentions": 3,
        "sentiment_score": 0.007,
        "sentiment_label": "Neutral",
        "sentiment_pct": 1,
        "counts": {
          "bullish": 1,
          "bearish": 1,
          "neutral": 1,
          "total": 3
        }
      },
      {
        "ticker": "ETH",
        "mentions": 2,
        "sentiment_score": -0.65,
        "sentiment_label": "Bearish",
        "sentiment_pct": 65,
        "counts": {
          "bullish": 0,
          "bearish": 2,
          "neutral": 0,
          "total": 2
        }
      },
      {
        "ticker": "BCH",
        "mentions": 1,
        "sentiment_score": 0.8,
        "sentiment_label": "Bullish",
        "sentiment_pct": 80,
        "counts": {
          "bullish": 1,
          "bearish": 0,
          "neutral": 0,
          "total": 1
        }
      },
      {
        "ticker": "XRP",
        "mentions": 1,
        "sentiment_score": 0.72,
        "sentiment_label": "Bullish",
        "sentiment_pct": 72,
        "counts": {
          "bullish": 1,
          "bearish": 0,
          "neutral": 0,
          "total": 1
        }
      }
    ],
    "other": [
      {
        "ticker": "TSLA",
        "mentions": 8,
        "sentiment_score": 0.443,
        "sentiment_label": "Bullish",
        "sentiment_pct": 44,
        "counts": {
          "bullish": 6,
          "bearish": 1,
          "neutral": 1,
          "total": 8
        }
      },
      {
        "ticker": "ORCL",
        "mentions": 8,
        "sentiment_score": 0.039,
        "sentiment_label": "Neutral",
        "sentiment_pct": 4,
        "counts": {
          "bullish": 4,
          "bearish": 4,
          "neutral": 0,
          "total": 8
        }
      },
      {
        "ticker": "AVGO",
        "mentions": 7,
        "sentiment_score": 0.553,
        "sentiment_label": "Bullish",
        "sentiment_pct": 55,
        "counts": {
          "bullish": 5,
          "bearish": 0,
          "neutral": 2,
          "total": 7
        }
      },
      {
        "ticker": "NVDA",
        "mentions": 7,
        "sentiment_score": 0.42,
        "sentiment_label": "Bullish",
        "sentiment_pct": 42,
        "counts": {
          "bullish": 5,
          "bearish": 1,
          "neutral": 1,
          "total": 7
        }
      },
      {
        "ticker": "SPX",
        "mentions": 6,
        "sentiment_score": 0.195,
        "sentiment_label": "Bullish",
        "sentiment_pct": 20,
        "counts": {
          "bullish": 2,
          "bearish": 1,
          "neutral": 3,
          "total": 6
        }
      }
    ]
  },
  "regime": {
    "label": "NEUTRAL",
    "color": "text-muted",
    "vix": 15.79,
    "pc_ratio": 1.11,
    "sentiment_bullish_pct": 39,
    "summary": "Market is lacking clear direction. Wait for confirmation."
  },
  "iv_opportunity": {
    "label": "FAIR VALUE",
    "color": "text-orange",
    "iv_rank": 30,
    "hv": 12.9,
    "spread": 10.83,
    "position": 50
  },
  "action": {
    "summary": "NEUTRAL: No clear edge. Cash is a position."
  }
}