{
  "timestamp": "2026-01-07T00:11:40.055Z",
  "hours_analyzed": 24,
  "sentiment": {
    "overall": "BULLISH",
    "confidence_pct": 82,
    "sources": {
      "social": {
        "bullish": 212,
        "bearish": 34,
        "neutral": 149,
        "total": 395,
        "pct": 54
      },
      "news": {
        "bullish": 50,
        "bearish": 24,
        "neutral": 21,
        "total": 95,
        "pct": 53
      },
      "video": {
        "bullish": 5,
        "bearish": 0,
        "neutral": 2,
        "total": 7,
        "pct": 71
      },
      "chat": {
        "bullish": 0,
        "bearish": 0,
        "neutral": 0,
        "total": 0,
        "pct": 0
      }
    }
  },
  "analysis": {
    "narrative": "📊 **Consensus:** Bullish sentiment with medium-high conviction across all sources (86% X, 68% RSS, 100% YouTube), though structural divergences in mega-cap tech create fragility beneath surface momentum.\n\n📈 **Themes:** (1) Semiconductor/AI structural demand driving tech selectivity amid mega-cap divergences, (2) Institutional crypto adoption momentum (tokenization, legislative tailwinds) competing with regulatory uncertainty, (3) Precious metals breakout continuation (gold/silver) signaling macro inflation hedging or policy normalization expectations.\n\n🎯 **Levels:** SPY ($691.81): Call Wall $750 (55k OI), Put Wall $630 (143k OI). Max Pain $687. Near resistance: $693 (48k OI - ACTIVE). Near support: $680 (85k OI - ACTIVE). QQQ ($623.42): Call Wall $641 (55k OI - ACTIVE), Put Wall $574.78 (116k OI). Max Pain $618. Near resistance: $627 (53k OI), $630 (33k OI). /ES: Triangle breakout decision point per Twitter analysis.",
    "key_tickers": [
      "SPY",
      "QQQ",
      "NVDA",
      "XRP",
      "AAPL",
      "NFLX",
      "OPEN",
      "TSLA",
      "AMD"
    ],
    "key_themes": [
      "AI/semiconductor structural demand and supply constraints",
      "Institutional crypto adoption and tokenization momentum",
      "Precious metals breakout continuation",
      "Mega-cap tech leadership divergence",
      "Sector rotation from traditional finance to growth/innovation assets"
    ],
    "risk_factors": [
      "Mega-cap tech divergence signaling potential leadership failure and broad reversal",
      "Regulatory uncertainty in crypto despite legislative momentum",
      "Geopolitical fragmentation affecting semiconductor supply chains and Venezuela crude policy execution",
      "Banking sector capital requirements and structural weakness in rate-sensitive sectors",
      "Overleveraged positioning in crypto/speculative assets creating liquidation risk"
    ],
    "intraday_bias": "NEUTRAL",
    "intraday_levels": "SPY: Active resistance $693 (48k OI), active support $680 (85k OI). QQQ: Active resistance $641 Call Wall (55k OI), testing $627 (53k OI). Max Pain gravitational pull: SPY $687, QQQ $618.",
    "swing_bias": "BULLISH",
    "swing_levels": "SPY: Call Wall resistance $750 (55k OI), Put Wall support $630 (143k OI). QQQ: Call Wall $641 (55k OI) as critical breakout level, Put Wall $574.78 (116k OI). Gold targeting $4,500+ per Twitter, silver targeting $82.50+ per Twitter.",
    "source_alignment": "MIXED"
  },
  "metadata": {
    "model": "AI Model",
    "generation_time_ms": 170466
  },
  "trending": {
    "macro": [
      {
        "ticker": "QQQ",
        "mentions": 13,
        "sentiment_score": 0.484,
        "sentiment_label": "Bullish",
        "sentiment_pct": 48,
        "counts": {
          "bullish": 9,
          "bearish": 1,
          "neutral": 3,
          "total": 13
        }
      },
      {
        "ticker": "SPY",
        "mentions": 9,
        "sentiment_score": 0.626,
        "sentiment_label": "Bullish",
        "sentiment_pct": 63,
        "counts": {
          "bullish": 8,
          "bearish": 1,
          "neutral": 0,
          "total": 9
        }
      },
      {
        "ticker": "SLV",
        "mentions": 3,
        "sentiment_score": 0.783,
        "sentiment_label": "Bullish",
        "sentiment_pct": 78,
        "counts": {
          "bullish": 3,
          "bearish": 0,
          "neutral": 0,
          "total": 3
        }
      },
      {
        "ticker": "DIA",
        "mentions": 1,
        "sentiment_score": 0.82,
        "sentiment_label": "Bullish",
        "sentiment_pct": 82,
        "counts": {
          "bullish": 1,
          "bearish": 0,
          "neutral": 0,
          "total": 1
        }
      },
      {
        "ticker": "IWM",
        "mentions": 1,
        "sentiment_score": 0.82,
        "sentiment_label": "Bullish",
        "sentiment_pct": 82,
        "counts": {
          "bullish": 1,
          "bearish": 0,
          "neutral": 0,
          "total": 1
        }
      }
    ],
    "crypto": [
      {
        "ticker": "BTC",
        "mentions": 10,
        "sentiment_score": 0.047,
        "sentiment_label": "Neutral",
        "sentiment_pct": 5,
        "counts": {
          "bullish": 3,
          "bearish": 3,
          "neutral": 4,
          "total": 10
        }
      },
      {
        "ticker": "MSTR",
        "mentions": 8,
        "sentiment_score": 0.657,
        "sentiment_label": "Bullish",
        "sentiment_pct": 66,
        "counts": {
          "bullish": 7,
          "bearish": 0,
          "neutral": 1,
          "total": 8
        }
      },
      {
        "ticker": "ETH",
        "mentions": 6,
        "sentiment_score": 0.355,
        "sentiment_label": "Bullish",
        "sentiment_pct": 36,
        "counts": {
          "bullish": 4,
          "bearish": 1,
          "neutral": 1,
          "total": 6
        }
      },
      {
        "ticker": "SOL",
        "mentions": 4,
        "sentiment_score": 0.193,
        "sentiment_label": "Bullish",
        "sentiment_pct": 19,
        "counts": {
          "bullish": 2,
          "bearish": 1,
          "neutral": 1,
          "total": 4
        }
      },
      {
        "ticker": "XRP",
        "mentions": 3,
        "sentiment_score": 0.54,
        "sentiment_label": "Bullish",
        "sentiment_pct": 54,
        "counts": {
          "bullish": 2,
          "bearish": 0,
          "neutral": 1,
          "total": 3
        }
      }
    ],
    "other": [
      {
        "ticker": "NVDA",
        "mentions": 14,
        "sentiment_score": 0.56,
        "sentiment_label": "Bullish",
        "sentiment_pct": 56,
        "counts": {
          "bullish": 11,
          "bearish": 1,
          "neutral": 2,
          "total": 14
        }
      },
      {
        "ticker": "TSLA",
        "mentions": 11,
        "sentiment_score": 0.228,
        "sentiment_label": "Bullish",
        "sentiment_pct": 23,
        "counts": {
          "bullish": 6,
          "bearish": 3,
          "neutral": 2,
          "total": 11
        }
      },
      {
        "ticker": "SPX",
        "mentions": 9,
        "sentiment_score": 0.43,
        "sentiment_label": "Bullish",
        "sentiment_pct": 43,
        "counts": {
          "bullish": 5,
          "bearish": 0,
          "neutral": 4,
          "total": 9
        }
      },
      {
        "ticker": "AMZN",
        "mentions": 8,
        "sentiment_score": 0.557,
        "sentiment_label": "Bullish",
        "sentiment_pct": 56,
        "counts": {
          "bullish": 7,
          "bearish": 1,
          "neutral": 0,
          "total": 8
        }
      },
      {
        "ticker": "RKLB",
        "mentions": 7,
        "sentiment_score": 0.799,
        "sentiment_label": "Bullish",
        "sentiment_pct": 80,
        "counts": {
          "bullish": 7,
          "bearish": 0,
          "neutral": 0,
          "total": 7
        }
      }
    ]
  },
  "regime": {
    "label": "NEUTRAL",
    "color": "text-muted",
    "vix": 14.75,
    "pc_ratio": 1.15,
    "sentiment_bullish_pct": 54,
    "summary": "Market is lacking clear direction. Wait for confirmation."
  },
  "iv_opportunity": {
    "label": "FAIR VALUE",
    "color": "text-orange",
    "iv_rank": 30,
    "hv": 8.84,
    "spread": 15.81,
    "position": 50
  },
  "action": {
    "summary": "NEUTRAL: No clear edge. Cash is a position."
  }
}